MANIFEST.in
marketing_campaign_data.xml
marketing_campaign_demo.xml
marketing_campaign_view.xml
marketing_campaign_workflow.xml
res_partner_view.xml
setup.py
./__init__.py
./__openerp__.py
./marketing_campaign.py
./res_partner.py
./report/__init__.py
./report/campaign_analysis.py
i18n/ar.po
i18n/bg.po
i18n/ca.po
i18n/cs.po
i18n/da.po
i18n/de.po
i18n/el.po
i18n/es.po
i18n/es_CR.po
i18n/es_MX.po
i18n/es_VE.po
i18n/fi.po
i18n/fr.po
i18n/he.po
i18n/hi.po
i18n/hr.po
i18n/hu.po
i18n/it.po
i18n/ja.po
i18n/lv.po
i18n/marketing_campaign.pot
i18n/mk.po
i18n/mn.po
i18n/nl.po
i18n/pl.po
i18n/pt.po
i18n/pt_BR.po
i18n/ro.po
i18n/ru.po
i18n/sl.po
i18n/sr@latin.po
i18n/sv.po
i18n/th.po
i18n/tr.po
i18n/zh_CN.po
images/campaign.png
images/campaigns.jpeg
images/email_account.jpeg
images/email_templates.jpeg
images/segments.jpeg
openerp_marketing_campaign.egg-info/PKG-INFO
openerp_marketing_campaign.egg-info/SOURCES.txt
openerp_marketing_campaign.egg-info/dependency_links.txt
openerp_marketing_campaign.egg-info/requires.txt
openerp_marketing_campaign.egg-info/top_level.txt
report/campaign_analysis_view.xml
security/ir.model.access.csv
security/marketing_campaign_security.xml
test/marketing_campaign.yml